LICENSE
MANIFEST.in
README.md
setup.py
tap_sendgrid/__init__.py
tap_sendgrid/context.py
tap_sendgrid/http.py
tap_sendgrid/streams.py
tap_sendgrid/syncs.py
tap_sendgrid/utils.py
tap_sendgrid.egg-info/PKG-INFO
tap_sendgrid.egg-info/SOURCES.txt
tap_sendgrid.egg-info/dependency_links.txt
tap_sendgrid.egg-info/entry_points.txt
tap_sendgrid.egg-info/requires.txt
tap_sendgrid.egg-info/top_level.txt
tap_sendgrid/schemas/blocks.json
tap_sendgrid/schemas/bounces.json
tap_sendgrid/schemas/campaigns.json
tap_sendgrid/schemas/contacts.json
tap_sendgrid/schemas/global_suppressions.json
tap_sendgrid/schemas/groups_all.json
tap_sendgrid/schemas/groups_members.json
tap_sendgrid/schemas/invalids.json
tap_sendgrid/schemas/lists_all.json
tap_sendgrid/schemas/lists_members.json
tap_sendgrid/schemas/segments_all.json
tap_sendgrid/schemas/segments_members.json
tap_sendgrid/schemas/spam_reports.json
tap_sendgrid/schemas/templates_all.json