Metadata-Version: 2.1
Name: tap-sendgrid
Version: 1.0.4
Summary: Singer.io tap for extracting data from the SendGrid API
Home-page: http://singer.io
Author: Stitch
Classifier: Programming Language :: Python :: 3 :: Only
License-File: LICENSE
